iros/__init__.py
iros/activations.py
iros/layers.py
iros/network.py
tests/__init__.py
tests/test_activations.py
tests/test_layers.py
tests/test_network.py
tests/test_save_load.py
iros-0.1.0.dist-info/LICENCE
iros-0.1.0.dist-info/METADATA
iros-0.1.0.dist-info/WHEEL
iros-0.1.0.dist-info/top_level.txt
iros-0.1.0.dist-info/RECORD
