Metadata-Version: 2.1
Name: iros
Version: 0.1.0
Summary: A simple neural network library
Home-page: https://github.com/RogerRos/iros
Author: Roger Ros
Author-email: rogerrosvidal@gmail.com
Classifier: Programming Language :: Python :: 3
Classifier: License :: OSI Approved :: MIT License
Classifier: Operating System :: OS Independent
Requires-Python: >=3.6
License-File: LICENCE
Requires-Dist: numpy
